vvuq/__init__.py
vvuq/client.py
vvuq/mcp_server.py
vvuq_client-0.2.0.dist-info/METADATA
vvuq_client-0.2.0.dist-info/WHEEL
vvuq_client-0.2.0.dist-info/entry_points.txt
vvuq_client-0.2.0.dist-info/top_level.txt
vvuq_client-0.2.0.dist-info/RECORD
