Metadata-Version: 2.4
Name: vvuq-client
Version: 0.2.0
Summary: Official Client SDK for the VVUQ Verification API
Author-email: Dirk Englund <englund@mit.edu>
License: MIT
Project-URL: Homepage, https://github.com/dirkenglund/vvuq-mcp
Project-URL: Documentation, https://github.com/dirkenglund/vvuq-mcp#readme
Requires-Python: >=3.10
Requires-Dist: requests>=2.28.0
Requires-Dist: fastmcp>=2.0.0
Requires-Dist: pydantic>=2.0.0
